linkml_transformer/__init__.py
linkml_transformer/cli/__init__.py
linkml_transformer/cli/cli.py
linkml_transformer/compiler/__init__.py
linkml_transformer/compiler/awk_compiler.py
linkml_transformer/compiler/compiler.py
linkml_transformer/compiler/graphviz_compiler.py
linkml_transformer/compiler/j2_based_compiler.py
linkml_transformer/compiler/markdown_compiler.py
linkml_transformer/compiler/python_compiler.py
linkml_transformer/compiler/r2rml_compiler.py
linkml_transformer/compiler/sparql_compiler.py
linkml_transformer/compiler/sql_compiler.py
linkml_transformer/compiler/sssom_compiler.py
linkml_transformer/compiler/templates/__init__.py
linkml_transformer/compiler/templates/markdown.j2
linkml_transformer/compiler/tr/__init__.py
linkml_transformer/compiler/tr/transformer_to_mapping_tables.tr.yaml
linkml_transformer/datamodel/__init__.py
linkml_transformer/datamodel/sssom.map.yaml
linkml_transformer/datamodel/transformer_model.py
linkml_transformer/datamodel/transformer_model.yaml
linkml_transformer/functions/__init__.py
linkml_transformer/functions/unit_conversion.py
linkml_transformer/importer/__init__.py
linkml_transformer/importer/importer.py
linkml_transformer/inference/__init__.py
linkml_transformer/inference/inference.py
linkml_transformer/inference/inverter.py
linkml_transformer/inference/schema_mapper.py
linkml_transformer/session.py
linkml_transformer/transformer/__init__.py
linkml_transformer/transformer/duckdb_transformer.py
linkml_transformer/transformer/object_transformer.py
linkml_transformer/transformer/transformer.py
linkml_transformer/utils/__init__.py
linkml_transformer/utils/dynamic_object.py
linkml_transformer/utils/eval_utils.py
linkml_transformer/utils/loaders.py
linkml_transformer/utils/multi_file_transformer.py
linkml_transformer-0.2.4.dist-info/METADATA
linkml_transformer-0.2.4.dist-info/WHEEL
linkml_transformer-0.2.4.dist-info/entry_points.txt
linkml_transformer-0.2.4.dist-info/RECORD
