Metadata-Version: 2.1
Name: linkml-transformer
Version: 0.2.4
Summary: 
Author: cmungall
Author-email: cjm@berkeleybop.org
Requires-Python: >=3.9,<4.0
Classifier: Programming Language :: Python :: 3
Classifier: Programming Language :: Python :: 3.9
Classifier: Programming Language :: Python :: 3.10
Classifier: Programming Language :: Python :: 3.11
Classifier: Programming Language :: Python :: 3.12
Requires-Dist: asteval (>=0.9.29,<0.10.0)
Requires-Dist: deepdiff (>=6.7.1,<7.0.0)
Requires-Dist: linkml-runtime (>=1.7.2)
Requires-Dist: pydantic (>=2.5.3,<3.0.0)
Requires-Dist: ucumvert (>=0.1.1,<0.2.0)
